[
  {
    "index": 1,
    "x1": 1310,
    "y1": 50,
    "x2": 1441,
    "y2": 296
  },
  {
    "index": 2,
    "x1": 1314,
    "y1": 305,
    "x2": 1427,
    "y2": 609
  },
  {
    "index": 3,
    "x1": 1335,
    "y1": 572,
    "x2": 1421,
    "y2": 890
  },
  {
    "index": 4,
    "x1": 1321,
    "y1": 895,
    "x2": 1435,
    "y2": 1038
  },
  {
    "index": 5,
    "x1": 1340,
    "y1": 1051,
    "x2": 1413,
    "y2": 1192
  },
  {
    "index": 6,
    "x1": 1144,
    "y1": 61,
    "x2": 1238,
    "y2": 199
  },
  {
    "index": 7,
    "x1": 1154,
    "y1": 185,
    "x2": 1262,
    "y2": 327
  },
  {
    "index": 8,
    "x1": 1152,
    "y1": 304,
    "x2": 1252,
    "y2": 480
  },
  {
    "index": 9,
    "x1": 1163,
    "y1": 434,
    "x2": 1258,
    "y2": 634
  },
  {
    "index": 10,
    "x1": 1145,
    "y1": 612,
    "x2": 1275,
    "y2": 896
  },
  {
    "index": 11,
    "x1": 1130,
    "y1": 921,
    "x2": 1245,
    "y2": 1046
  },
  {
    "index": 12,
    "x1": 1149,
    "y1": 1056,
    "x2": 1275,
    "y2": 1228
  },
  {
    "index": 13,
    "x1": 975,
    "y1": 40,
    "x2": 1088,
    "y2": 354
  },
  {
    "index": 14,
    "x1": 961,
    "y1": 354,
    "x2": 1084,
    "y2": 678
  },
  {
    "index": 15,
    "x1": 954,
    "y1": 647,
    "x2": 1078,
    "y2": 846
  },
  {
    "index": 16,
    "x1": 935,
    "y1": 837,
    "x2": 1074,
    "y2": 1264
  }
]